{
	"info": {
		"_postman_id": "9f778865-8171-46a0-ace3-804a89d0e84e",
		"name": "Cfn-Subdomain",
		"schema": "https://schema.getpostman.com/json/collection/v2.1.0/collection.json",
		"_exporter_id": "30805301"
	},
	"item": [
		{
			"name": "truyen full",
			"item": [
				{
					"name": "Store new link",
					"request": {
						"method": "POST",
						"header": [
							{
								"key": "Accept",
								"value": "application/json",
								"type": "text"
							},
							{
								"warning": "This is a duplicate header and will be overridden by the Content-Type header generated by Postman.",
								"key": "Content-Type",
								"value": "application/json",
								"type": "text"
							}
						],
						"body": {
							"mode": "raw",
							"raw": "{\r\n    \"urls\": [\r\n        \"https://truyenfull.com/mat-ngot-hon-nhan-f6.17999\",\r\n        \"https://truyenfull.com/mat-ngot-hon-nhan-f6.17999/trang-2/#chapter-list\",\r\n        \"https://truyenfull.com/mat-ngot-hon-nhan-f6.17999/trang-3/#chapter-list\",\r\n        \"https://truyenfull.com/mat-ngot-hon-nhan-f6.17999/trang-4/#chapter-list\",\r\n        \"https://truyenfull.com/mat-ngot-hon-nhan-f6.17999/trang-5/#chapter-list\",\r\n        \"https://truyenfull.com/mat-ngot-hon-nhan-f6.17999/trang-6/#chapter-list\"\r\n    ]\r\n}"
						},
						"url": {
							"raw": "{{local_url}}/api/tf/craw-new-story",
							"host": [
								"{{local_url}}"
							],
							"path": [
								"api",
								"tf",
								"craw-new-story"
							]
						}
					},
					"response": []
				},
				{
					"name": "Crawl chapters",
					"request": {
						"method": "POST",
						"header": [
							{
								"key": "Accept",
								"value": "application/json",
								"type": "text"
							},
							{
								"warning": "This is a duplicate header and will be overridden by the Content-Type header generated by Postman.",
								"key": "Content-Type",
								"value": "application/json",
								"type": "text"
							}
						],
						"body": {
							"mode": "raw",
							"raw": "{\r\n    \"urls\": [\r\n        \"https://truyenfull.com/mat-ngot-hon-nhan-f6.17999\",\r\n        \"https://truyenfull.com/mat-ngot-hon-nhan-f6.17999/trang-2/#chapter-list\"\r\n    ]\r\n}"
						},
						"url": {
							"raw": "{{local_url}}/api/tf/craw-link-chapters",
							"host": [
								"{{local_url}}"
							],
							"path": [
								"api",
								"tf",
								"craw-link-chapters"
							]
						}
					},
					"response": []
				},
				{
					"name": "Crawl content chapter",
					"request": {
						"method": "POST",
						"header": [
							{
								"key": "Accept",
								"value": "application/json",
								"type": "text"
							},
							{
								"warning": "This is a duplicate header and will be overridden by the Content-Type header generated by Postman.",
								"key": "Content-Type",
								"value": "application/json",
								"type": "text"
							}
						],
						"body": {
							"mode": "formdata",
							"formdata": [
								{
									"key": "url",
									"value": "https://truyenfull.com/mat-ngot-hon-nhan/chuong-1.html",
									"type": "text"
								}
							]
						},
						"url": {
							"raw": "{{local_url}}/api/tf/craw-content-chapter",
							"host": [
								"{{local_url}}"
							],
							"path": [
								"api",
								"tf",
								"craw-content-chapter"
							]
						}
					},
					"response": []
				}
			]
		},
		{
			"name": "dtruyen",
			"item": [
				{
					"name": "Store new link",
					"request": {
						"method": "POST",
						"header": [
							{
								"key": "Accept",
								"value": "application/json",
								"type": "text"
							},
							{
								"warning": "This is a duplicate header and will be overridden by the Content-Type header generated by Postman.",
								"key": "Content-Type",
								"value": "application/json",
								"type": "text"
							}
						],
						"body": {
							"mode": "raw",
							"raw": "{\r\n    \"urls\": [\r\n        \"https://dtruyen.com/xuyen-toi-70-thon-co-cuc-pham-khong-de-choc/\"\r\n    ]\r\n}"
						},
						"url": {
							"raw": "{{pro_url}}/api/dt/craw-new-story",
							"host": [
								"{{pro_url}}"
							],
							"path": [
								"api",
								"dt",
								"craw-new-story"
							]
						}
					},
					"response": []
				},
				{
					"name": "Crawl chapters",
					"request": {
						"method": "POST",
						"header": [
							{
								"key": "Accept",
								"value": "application/json",
								"type": "text"
							},
							{
								"warning": "This is a duplicate header and will be overridden by the Content-Type header generated by Postman.",
								"key": "Content-Type",
								"value": "application/json",
								"type": "text"
							}
						],
						"body": {
							"mode": "raw",
							"raw": "{\r\n    \"urls\": [\r\n        \"https://dtruyen.com/em-gai-diu-dang-va-anh-trai-ma-quy/\",\r\n        \"https://dtruyen.com/xuyen-toi-70-thon-co-cuc-pham-khong-de-choc/2/\",\r\n        \"https://dtruyen.com/xuyen-toi-70-thon-co-cuc-pham-khong-de-choc/3/\",\r\n        \"https://dtruyen.com/xuyen-toi-70-thon-co-cuc-pham-khong-de-choc/4/\",\r\n        \"https://dtruyen.com/xuyen-toi-70-thon-co-cuc-pham-khong-de-choc/5/\",\r\n        \"https://dtruyen.com/xuyen-toi-70-thon-co-cuc-pham-khong-de-choc/6/\",\r\n        \"https://dtruyen.com/xuyen-toi-70-thon-co-cuc-pham-khong-de-choc/7/\",\r\n        \"https://dtruyen.com/xuyen-toi-70-thon-co-cuc-pham-khong-de-choc/8/\",\r\n        \"https://dtruyen.com/xuyen-toi-70-thon-co-cuc-pham-khong-de-choc/9/\",\r\n        \"https://dtruyen.com/xuyen-toi-70-thon-co-cuc-pham-khong-de-choc/10/\",\r\n        \"https://dtruyen.com/xuyen-toi-70-thon-co-cuc-pham-khong-de-choc/11/\"\r\n    ]\r\n}"
						},
						"url": {
							"raw": "{{pro_url}}/api/dt/craw-link-chapters",
							"host": [
								"{{pro_url}}"
							],
							"path": [
								"api",
								"dt",
								"craw-link-chapters"
							]
						}
					},
					"response": []
				},
				{
					"name": "Crawl content chapter",
					"request": {
						"method": "POST",
						"header": [
							{
								"key": "Accept",
								"value": "application/json",
								"type": "text"
							},
							{
								"warning": "This is a duplicate header and will be overridden by the Content-Type header generated by Postman.",
								"key": "Content-Type",
								"value": "application/json",
								"type": "text"
							}
						],
						"body": {
							"mode": "formdata",
							"formdata": [
								{
									"key": "url",
									"value": "https://dtruyen.com/em-gai-diu-dang-va-anh-trai-ma-quy/em-gai-giup-anh-trai-tam_866602.html",
									"type": "text"
								}
							]
						},
						"url": {
							"raw": "{{local_url}}/api/dt/craw-content-chapter",
							"host": [
								"{{local_url}}"
							],
							"path": [
								"api",
								"dt",
								"craw-content-chapter"
							]
						}
					},
					"response": []
				}
			]
		}
	]
}